{
  "id": "772148",
  "name": "私人-表格组件图标",
  "font_family": "iconfont",
  "css_prefix_text": "ss-icon-",
  "description": "表格组件图标",
  "glyphs": [
    {
      "icon_id": "7127384",
      "name": "加载",
      "font_class": "jiazai",
      "unicode": "e607",
      "unicode_decimal": 58887
    },
    {
      "icon_id": "5831392",
      "name": "排序",
      "font_class": "paixu",
      "unicode": "e66c",
      "unicode_decimal": 58988
    },
    {
      "icon_id": "1237612",
      "name": "多人拼团",
      "font_class": "duorenpintuan",
      "unicode": "e64d",
      "unicode_decimal": 58957
    },
    {
      "icon_id": "4334160",
      "name": "房子",
      "font_class": "fangzi",
      "unicode": "e622",
      "unicode_decimal": 58914
    },
    {
      "icon_id": "8654082",
      "name": "五角星 全星",
      "font_class": "wujiaoxingquanxing",
      "unicode": "e6df",
      "unicode_decimal": 59103
    },
    {
      "icon_id": "11175131",
      "name": "五角星 星型 ",
      "font_class": "wujiaoxingxingxing",
      "unicode": "e6e0",
      "unicode_decimal": 59104
    },
    {
      "icon_id": "1803266",
      "name": "感叹号",
      "font_class": "gantanhao1",
      "unicode": "e6dc",
      "unicode_decimal": 59100
    },
    {
      "icon_id": "12649046",
      "name": "必填 (1)",
      "font_class": "bitian",
      "unicode": "e6d9",
      "unicode_decimal": 59097
    },
    {
      "icon_id": "3181207",
      "name": "复选框",
      "font_class": "checkbox",
      "unicode": "e711",
      "unicode_decimal": 59153
    },
    {
      "icon_id": "10091876",
      "name": "全选",
      "font_class": "checkbox-all",
      "unicode": "e6da",
      "unicode_decimal": 59098
    },
    {
      "icon_id": "10191792",
      "name": "单选选中",
      "font_class": "radio-checked2",
      "unicode": "e6d7",
      "unicode_decimal": 59095
    },
    {
      "icon_id": "645039",
      "name": "搜索",
      "font_class": "sousuo",
      "unicode": "e64c",
      "unicode_decimal": 58956
    },
    {
      "icon_id": "845785",
      "name": "完成 (1)",
      "font_class": "wancheng11",
      "unicode": "e6d8",
      "unicode_decimal": 59096
    },
    {
      "icon_id": "1234964",
      "name": "向上",
      "font_class": "xiangshang",
      "unicode": "e80e",
      "unicode_decimal": 59406
    },
    {
      "icon_id": "1234965",
      "name": "向下",
      "font_class": "xiangxia",
      "unicode": "e80f",
      "unicode_decimal": 59407
    },
    {
      "icon_id": "1304877",
      "name": "更多",
      "font_class": "gengduo",
      "unicode": "e621",
      "unicode_decimal": 58913
    },
    {
      "icon_id": "1305406",
      "name": "上",
      "font_class": "shang",
      "unicode": "e63c",
      "unicode_decimal": 58940
    },
    {
      "icon_id": "1305407",
      "name": "下",
      "font_class": "xia",
      "unicode": "e63d",
      "unicode_decimal": 58941
    },
    {
      "icon_id": "1305408",
      "name": "左",
      "font_class": "zuo",
      "unicode": "e63e",
      "unicode_decimal": 58942
    },
    {
      "icon_id": "1509738",
      "name": "取消",
      "font_class": "cancel",
      "unicode": "e6de",
      "unicode_decimal": 59102
    },
    {
      "icon_id": "1718351",
      "name": "上箭头",
      "font_class": "shangjiantou",
      "unicode": "e600",
      "unicode_decimal": 58880
    },
    {
      "icon_id": "1718353",
      "name": "下箭头",
      "font_class": "xiajiantou",
      "unicode": "e601",
      "unicode_decimal": 58881
    },
    {
      "icon_id": "1718355",
      "name": "右箭头",
      "font_class": "youjiantou",
      "unicode": "e602",
      "unicode_decimal": 58882
    },
    {
      "icon_id": "1718358",
      "name": "左箭头",
      "font_class": "zuojiantou",
      "unicode": "e603",
      "unicode_decimal": 58883
    },
    {
      "icon_id": "4447201",
      "name": "单选 选中",
      "font_class": "radio-checked",
      "unicode": "e6e3",
      "unicode_decimal": 59107
    },
    {
      "icon_id": "6056149",
      "name": "编辑",
      "font_class": "bianji2",
      "unicode": "e6e4",
      "unicode_decimal": 59108
    },
    {
      "icon_id": "9143725",
      "name": "单选 选中",
      "font_class": "radio",
      "unicode": "e6e6",
      "unicode_decimal": 59110
    },
    {
      "icon_id": "9495637",
      "name": "复选框",
      "font_class": "checkbox-checked",
      "unicode": "e71e",
      "unicode_decimal": 59166
    }
  ]
}
